horde_sdk/__init__.py
horde_sdk/_version.py
horde_sdk/consts.py
horde_sdk/exceptions.py
horde_sdk/horde_logging.py
horde_sdk/localize.py
horde_sdk/meta.py
horde_sdk/py.typed
horde_sdk/utils.py
horde_sdk/ai_horde_api/__init__.py
horde_sdk/ai_horde_api/ai_horde_clients.py
horde_sdk/ai_horde_api/consts.py
horde_sdk/ai_horde_api/endpoints.py
horde_sdk/ai_horde_api/exceptions.py
horde_sdk/ai_horde_api/fields.py
horde_sdk/ai_horde_api/kudos.py
horde_sdk/ai_horde_api/metadata.py
horde_sdk/ai_horde_api/server_model_names.py
horde_sdk/ai_horde_api/apimodels/__init__.py
horde_sdk/ai_horde_api/apimodels/_documents.py
horde_sdk/ai_horde_api/apimodels/_find_user.py
horde_sdk/ai_horde_api/apimodels/_kudos.py
horde_sdk/ai_horde_api/apimodels/_stats.py
horde_sdk/ai_horde_api/apimodels/_status.py
horde_sdk/ai_horde_api/apimodels/_styles.py
horde_sdk/ai_horde_api/apimodels/_users.py
horde_sdk/ai_horde_api/apimodels/base.py
horde_sdk/ai_horde_api/apimodels/alchemy/__init__.py
horde_sdk/ai_horde_api/apimodels/alchemy/_async.py
horde_sdk/ai_horde_api/apimodels/alchemy/_pop.py
horde_sdk/ai_horde_api/apimodels/alchemy/_status.py
horde_sdk/ai_horde_api/apimodels/alchemy/_submit.py
horde_sdk/ai_horde_api/apimodels/generate/__init__.py
horde_sdk/ai_horde_api/apimodels/generate/_async.py
horde_sdk/ai_horde_api/apimodels/generate/_check.py
horde_sdk/ai_horde_api/apimodels/generate/_pop.py
horde_sdk/ai_horde_api/apimodels/generate/_progress.py
horde_sdk/ai_horde_api/apimodels/generate/_status.py
horde_sdk/ai_horde_api/apimodels/generate/_submit.py
horde_sdk/ai_horde_api/apimodels/generate/text/__init__.py
horde_sdk/ai_horde_api/apimodels/generate/text/_async.py
horde_sdk/ai_horde_api/apimodels/generate/text/_pop.py
horde_sdk/ai_horde_api/apimodels/generate/text/_status.py
horde_sdk/ai_horde_api/apimodels/generate/text/_submit.py
horde_sdk/ai_horde_api/apimodels/workers/__init__.py
horde_sdk/ai_horde_api/apimodels/workers/_workers.py
horde_sdk/ai_horde_worker/__init__.py
horde_sdk-0.18.0.dist-info/licenses/LICENSE
horde_sdk-0.18.0.dist-info/METADATA
horde_sdk-0.18.0.dist-info/WHEEL
horde_sdk-0.18.0.dist-info/top_level.txt
horde_sdk-0.18.0.dist-info/RECORD
