Metadata-Version: 2.4
Name: horde_sdk
Version: 0.18.0
Summary: A python toolkit for interacting with the horde APIs, services, and ecosystem.
Author-email: tazlin <tazlin.on.github@gmail.com>, db0 <mail@dbzer0.com>
License: GNU AFFERO GENERAL PUBLIC LICENSE
Project-URL: Homepage, https://github.com/Haidra-Org/horde-sdk
Classifier: Programming Language :: Python :: 3
Classifier: Operating System :: OS Independent
Classifier: License :: OSI Approved :: GNU Affero General Public License v3
Classifier: Development Status :: 4 - Beta
Requires-Python: >=3.10
License-File: LICENSE
Requires-Dist: horde_model_reference>=2.0.0
Requires-Dist: pydantic>=2.9.2
Requires-Dist: requests
Requires-Dist: StrEnum
Requires-Dist: loguru
Requires-Dist: certifi
Requires-Dist: aiohttp
Requires-Dist: aiofiles
Requires-Dist: aiodns
Requires-Dist: pillow
Requires-Dist: python-dotenv
Dynamic: license-file
